{
  "text": "[SHEET: RFP ODDO BHF]\nUnnamed: 0 Unnamed: 1 Unnamed: 2 Unnamed: 3 Unnamed: 4 Unnamed: 5\n \n Procurement REF: 14_2025 \n Job Title IT Project Manager \n Job Title's Detail Project Manager Encryption \n Department IT Infrastructure & IT Operations \n \n \n Company Name \n Identifier of profile \n Answer date \n Nb years of experience\\nexcl intershipts / etc \n \n Answer established with the candidate \n Reason for the termination of the last experience \n Feedback/reference of previous client \n \n Freelance / Employee \n If freelance, how many years have you (the company) worked with the freelance ? \n Daily rate( €/d excl. taxes) \n \n \n Context The IT dept of ODDO BHF is currenlty delivering DORA regulatory project with a major stream related to Encryption.\\n\\nWe are searching for a project manager to \\n- Define and Steer the defined actions plan.\\n- Manage a RFP regarding tooling KMS, PKI, HSM & CLM.\\n- Organize & follow the deployment of target Encyption tools, chosen during the RFP.\\n- Contribute to the update of technical procedures with internal skill teams\\n- Manage the synchronization between the different teams and follow-up and report on progress\\n\\nYou will integrate this project and will represent the DORA \"Encryption\" stream as a member of IT Cybersecurity in all committees. You will have to ensure the good delivery of regulatory requirements in the project.\\n\\nYou will strongly collaborate with different IT Teams (IT Cybersecurity, IT Operations, IT Development, IT Business Vertical), as well as the 2nd line of defense IRM. \n Matching assessment\n Background Profile experience must meet the minimal requirements: Input a value from 0 (min) to 3 (max)\n The Group's IT teams are made up of more than 600 employees spread across Paris, Tunis, Frankfurt and Düsseldorf. 0..3\n We are looking for a project manager with a significant experience (more than 8 years) in the coordination of IT projects involving technical experts in a regulatory context. 0..3\n Knowledge in Encryption (certificates & keys) 0..3\n IT Infrastructure & security knowledge 0..3\n \n Detailed roles Expectations Matching assessment\n Project activity \n Coordinate, challenge, organize and manage IT teams involved in the project 0..3\n Animate meetings and committees with project teams and management 0..3\n Draft reportingt for project & steering committee 0..3\n Establish & manage the budget associated to the project 0..3\n \n Manage the communication and the reporting to committees 0..3\n Keep traceability of all meeting decisions via minutes 0..3\n \n Education Bac +5 graduated mandatory input the name and year of graduation\n \n Expected skills Knowledge foundation \n Solid technical background in infrastructure technologies & in Security Topics (encryption) 0..3\n \n Skills foundation \n English proficiency 0..3\n Project management methodology 0..3\n Budget construction 0..3\n People management 0..3\n \n Mindset foundation \n Good communication skills (fluent in English and French, written and spoken) 0..3\n Diplomacy, flexibility, Power of persuasion, Intellectual curiosity 0..3\n Highly skilled in oral and written communication 0..3\n team oriented 0..3\n \n Optional bonus criterias \n DORA Regulations 0..3\n Technical knowledge of encryption 0..3\n Excellent project management skills high cultural context 0..3\n \n Estimated duration of the mission One to one and half years \n \n Start date Asap input the estimated starting date\n \n \n Workplace\\n- \\nRemote work 3d / week Rue du General Leclerc, Clichy la Garenne \n Remote working 2d/week in average \n \n International business travel supported by Oddo, average stays of 2-3 days: \n · Germany: Frankfurt 1 or 2 times at the beginning to meet the team) \n · Tunisia : Tunis (1 or 2 times at the beginning to meet the team) \n \n \n \n \n \n \n \n \n \n 0\n 1\n 2\n 3\n\n[SHEET: Refs]\nUnnamed: 0 match score answers Unnamed: 3 Job Title Unnamed: 5 Department Unnamed: 7 Freelance / Employee\n 0.0 yes Desktop Engineer Digital Worplace Freelance\n 1.0 no Expert IT Business Verticals Employee\n 2.0 IT Business Support Infrastructure & IT Operations \n 3.0 Database Administrator Software Development Factory & Architecture \n System Administrator Transversal Functions \n Technician \n Production engineer \n Network Administrator \n Application Integration Administrator \n IT Business Analyst \n IT Architect \n Developer \n IT PMO \n IT Project Manager \n IT Governance officer",
  "skills": [
    {
      "name": "Project Management",
      "type": "functional",
      "family": "MOA"
    },
    {
      "name": "DORA Regulations",
      "type": "functional",
      "family": "MOA"
    },
    {
      "name": "Encryption",
      "type": "technical",
      "family": "MOE"
    },
    {
      "name": "KMS (Key Management System)",
      "type": "technical",
      "family": "MOE"
    },
    {
      "name": "PKI (Public Key Infrastructure)",
      "type": "technical",
      "family": "MOE"
    },
    {
      "name": "HSM (Hardware Security Module)",
      "type": "technical",
      "family": "MOE"
    },
    {
      "name": "CLM (Certificate Lifecycle Management)",
      "type": "technical",
      "family": "MOE"
    },
    {
      "name": "IT Cybersecurity",
      "type": "technical",
      "family": "MOE"
    },
    {
      "name": "IT Infrastructure",
      "type": "technical",
      "family": "MOE"
    },
    {
      "name": "IT Security",
      "type": "technical",
      "family": "MOE"
    },
    {
      "name": "IT Operations",
      "type": "technical",
      "family": "MOE"
    },
    {
      "name": "IT Development",
      "type": "technical",
      "family": "MOE"
    },
    {
      "name": "Information Risk Management (IRM)",
      "type": "functional",
      "family": "MOA"
    },
    {
      "name": "Project Management Methodology",
      "type": "functional",
      "family": "MOA"
    },
    {
      "name": "Budget Management",
      "type": "functional",
      "family": "MOA"
    },
    {
      "name": "People Management",
      "type": "functional",
      "family": "MOA"
    },
    {
      "name": "English",
      "type": "functional",
      "family": "MOA"
    },
    {
      "name": "French",
      "type": "functional",
      "family": "MOA"
    },
    {
      "name": "Communication",
      "type": "functional",
      "family": "MOA"
    },
    {
      "name": "Diplomacy",
      "type": "functional",
      "family": "MOA"
    },
    {
      "name": "Flexibility",
      "type": "functional",
      "family": "MOA"
    },
    {
      "name": "Persuasion",
      "type": "functional",
      "family": "MOA"
    },
    {
      "name": "Intellectual Curiosity",
      "type": "functional",
      "family": "MOA"
    },
    {
      "name": "Teamwork",
      "type": "functional",
      "family": "MOA"
    }
  ],
  "tasks": {
    "tasks": [
      "Définir les plans d'actions",
      "Piloter les plans d'actions",
      "Gérer les appels d'offres (RFP)",
      "Organiser le déploiement d'outils",
      "Suivre le déploiement d'outils",
      "Mettre à jour les procédures techniques",
      "Gérer la synchronisation entre les équipes",
      "Suivre l'avancement des projets",
      "Rapporter l'avancement des projets",
      "Représenter le projet (stream DORA Encryption) dans les comités",
      "Assurer la livraison des exigences réglementaires",
      "Coordonner les équipes IT",
      "Challenger les équipes IT",
      "Organiser les équipes IT",
      "Gérer les équipes IT",
      "Animer les réunions et comités",
      "Rédiger les rapports de projet et de comité de pilotage",
      "Établir le budget du projet",
      "Gérer le budget du projet",
      "Gérer la communication projet",
      "Maintenir la traçabilité des décisions de réunion",
      "Rédiger les procès-verbaux de réunion"
    ]
  },
  "cache": "miss"
}